rigging/__init__.py
rigging/__main__.py
rigging/application/__init__.py
rigging/application/discovery.py
rigging/application/services.py
rigging/cli/__init__.py
rigging/cli/completion.py
rigging/cli/configure.py
rigging/cli/discover.py
rigging/cli/execute.py
rigging/cli/logs.py
rigging/cli/main.py
rigging/cli/template.py
rigging/cli/utils.py
rigging/cli/validate.py
rigging/domain/__init__.py
rigging/domain/exceptions.py
rigging/domain/models.py
rigging/infrastructure/__init__.py
rigging/infrastructure/database.py
rigging/infrastructure/repositories.py
rigging/presentation/__init__.py
rigging/presentation/tui.py
rigging/schemas/claude-settings.schema.json
rigging_cli-0.1.2.dist-info/licenses/LICENSE
rigging_cli-0.1.2.dist-info/METADATA
rigging_cli-0.1.2.dist-info/WHEEL
rigging_cli-0.1.2.dist-info/entry_points.txt
rigging_cli-0.1.2.dist-info/top_level.txt
rigging_cli-0.1.2.dist-info/RECORD
