Metadata-Version: 2.4
Name: rigging-cli
Version: 0.1.2
Summary: Hook orchestration system for AI agents - All hands to the rigging!
Author: Brian Morin
License: MIT
Project-URL: Homepage, https://github.com/bdmorin/rigging-cli
Project-URL: Documentation, https://github.com/bdmorin/rigging-cli#readme
Project-URL: Repository, https://github.com/bdmorin/rigging-cli
Project-URL: Issues, https://github.com/bdmorin/rigging-cli/issues
Keywords: hooks,ai,automation,orchestration,claude-code
Classifier: Development Status :: 3 - Alpha
Classifier: Intended Audience :: Developers
Classifier: Programming Language :: Python :: 3.11
Classifier: Programming Language :: Python :: 3.12
Classifier: Topic :: Software Development :: Libraries :: Python Modules
Requires-Python: >=3.11
License-File: LICENSE
Requires-Dist: click>=8.1.7
Requires-Dist: textual>=0.47.0
Requires-Dist: claude-code-sdk>=0.0.17
Requires-Dist: sqlalchemy>=2.0.23
Requires-Dist: rich>=13.7.0
Requires-Dist: pydantic>=2.5.0
Requires-Dist: pydantic-settings>=2.1.0
Requires-Dist: httpx>=0.25.2
Requires-Dist: watchdog>=3.0.0
Requires-Dist: jinja2>=3.1.2
Requires-Dist: jsonschema>=4.20.0
Provides-Extra: completion
Requires-Dist: click-completion>=0.5.2; extra == "completion"
Requires-Dist: psutil>=5.9.0; extra == "completion"
Provides-Extra: dev
Requires-Dist: pytest>=7.4.0; extra == "dev"
Requires-Dist: pytest-cov>=4.1.0; extra == "dev"
Requires-Dist: black>=23.0.0; extra == "dev"
Requires-Dist: ruff>=0.1.0; extra == "dev"
Dynamic: license-file
